simplygithub/__init__.py
simplygithub/branches.py
simplygithub/files.py
simplygithub/authentication/__init__.py
simplygithub/authentication/constants.py
simplygithub/authentication/profile.py
simplygithub/internals/__init__.py
simplygithub/internals/api.py
simplygithub/internals/blobs.py
simplygithub/internals/commits.py
simplygithub/internals/constants.py
simplygithub/internals/merges.py
simplygithub/internals/refs.py
simplygithub/internals/trees.py
simplygithub-0.2.0.dist-info/DESCRIPTION.rst
simplygithub-0.2.0.dist-info/METADATA
simplygithub-0.2.0.dist-info/RECORD
simplygithub-0.2.0.dist-info/WHEEL
simplygithub-0.2.0.dist-info/metadata.json
simplygithub-0.2.0.dist-info/top_level.txt
